{
  "__base_type": "GameEffectRemoveBuff",
  "based_on": "GameEffectRemoveBuff",
  "buff": "duckiesBossXTier3Cast_CDBuff",
  "editor_icon": "",
  "effect_target": {
    "effect_parent": "none",
    "target": "Target"
  },
  "id": "duckiesBossXTier3Cast_CDBuffRemove",
  "impact_fx": "",
  "source_match": "None",
  "stacks": 1,
  "stacks_expression": {},
  "store_value": {
    "add_to_existing": true,
    "effect_parent": "",
    "store_name": ""
  },
  "tag_filter": {
    "alignment": "All",
    "ignored": [],
    "required": []
  },
  "target": "Target",
  "tracker": "",
  "validator": "emptyRef"
}