{
  "__base_type": "GameEffectModifyVitals",
  "based_on": "BaseGameEffectModifyVitals",
  "effect_target": {
    "effect_parent": "none",
    "target": "Target"
  },
  "energy_mod_expression": {},
  "energy_mod_flat_amount": 0.0,
  "energy_mod_percentage": 0.0,
  "health_mod_expression": {},
  "health_mod_flat_amount": 0.0,
  "health_mod_percentage": 7.0,
  "id": "duckiesBossXCallGolds_WarpHealthGain",
  "impact_fx": "",
  "shield_mod_expression": {},
  "shield_mod_flat_amount": 0.0,
  "shield_mod_percentage": 0.0,
  "tracker": "",
  "validator": "emptyRef"
}